{
  "type": "collection",
  "entry": [
    {
      "fullUrl": "urn:uuid:5b81597d-5c6a-47d5-aef1-450bedcb2fb1",
      "resource": {
        "id": "5b81597d-5c6a-47d5-aef1-450bedcb2fb1",
        "meta": {
          "profile": [
            "http://standardhealthrecord.org/fhir/StructureDefinition/shr-demographics-PersonOfRecord"
          ]
        },
        "text": {
          "status": "generated",
          "div": "<div>Generated by <a href=\"https://github.com/synthetichealth/synthea\">Synthea</a>. Version identifier: 4d02400401b9fab839e47bf5b2f1f6a8c683ab55</div>"
        },
        "extension": [
          {
            "url": "http://hl7.org/fhir/us/core/StructureDefinition/us-core-race",
            "valueCodeableConcept": {
              "coding": [
                {
                  "system": "http://hl7.org/fhir/v3/Race",
                  "code": "2028-9",
                  "display": "Asian"
                }
              ],
              "text": "race"
            }
          },
          {
            "url": "http://hl7.org/fhir/us/core/StructureDefinition/us-core-ethnicity",
            "valueCodeableConcept": {
              "coding": [
                {
                  "system": "http://hl7.org/fhir/v3/Ethnicity",
                  "code": "2186-5",
                  "display": "Nonhispanic"
                }
              ],
              "text": "ethnicity"
            }
          },
          {
            "url": "http://hl7.org/fhir/StructureDefinition/birthPlace",
            "valueAddress": {
              "city": "Marlborough",
              "state": "MA",
              "country": "US"
            }
          },
          {
            "url": "http://hl7.org/fhir/StructureDefinition/patient-mothersMaidenName",
            "valueString": "Mckenzie980 Lesch873"
          },
          {
            "url": "http://hl7.org/fhir/us/core/StructureDefinition/us-core-birthsex",
            "valueCode": "M"
          },
          {
            "url": "http://hl7.org/fhir/StructureDefinition/patient-interpreterRequired",
            "valueBoolean": false
          },
          {
            "url": "http://standardhealthrecord.org/fhir/StructureDefinition/shr-actor-FictionalPerson-extension",
            "valueBoolean": true
          },
          {
            "url": "http://standardhealthrecord.org/fhir/StructureDefinition/shr-demographics-FathersName-extension",
            "valueHumanName": {
              "text": "Andrew353 Ankunding739"
            }
          },
          {
            "url": "http://standardhealthrecord.org/fhir/StructureDefinition/shr-demographics-SocialSecurityNumber-extension",
            "valueString": "999-19-3004"
          }
        ],
        "identifier": [
          {
            "system": "https://github.com/synthetichealth/synthea",
            "value": "0df12049-19f6-4d92-9aa1-8a5fbdc3618e"
          },
          {
            "type": {
              "coding": [
                {
                  "system": "http://hl7.org/fhir/identifier-type",
                  "code": "SB"
                }
              ]
            },
            "system": "http://hl7.org/fhir/sid/us-ssn",
            "value": "999193004"
          },
          {
            "type": {
              "coding": [
                {
                  "system": "http://hl7.org/fhir/v2/0203",
                  "code": "DL"
                }
              ]
            },
            "system": "urn:oid:2.16.840.1.113883.4.3.25",
            "value": "S99916794"
          }
        ],
        "name": [
          {
            "use": "official",
            "family": "Ankunding739",
            "given": [
              "Leonor21"
            ],
            "prefix": [
              "Mr."
            ]
          }
        ],
        "telecom": [
          {
            "system": "phone",
            "value": "1-956-858-2954 x16880",
            "use": "home"
          }
        ],
        "gender": "male",
        "birthDate": "1994-11-03",
        "address": [
          {
            "extension": [
              {
                "extension": [
                  {
                    "url": "latitude",
                    "valueDecimal": 42.253937889480554
                  },
                  {
                    "url": "longitude",
                    "valueDecimal": -71.33573631230796
                  }
                ],
                "url": "http://hl7.org/fhir/StructureDefinition/geolocation"
              }
            ],
            "line": [
              "78598 Burdette Roads"
            ],
            "city": "Natick",
            "state": "MA",
            "postalCode": "01760",
            "country": "US"
          }
        ],
        "maritalStatus": {
          "coding": [
            {
              "system": "http://hl7.org/fhir/v3/MaritalStatus",
              "code": "S"
            }
          ],
          "text": "Never Married"
        },
        "multipleBirthBoolean": false,
        "communication": [
          {
            "language": {
              "coding": [
                {
                  "system": "http://hl7.org/fhir/ValueSet/languages",
                  "code": "en-US",
                  "display": "English (United States)"
                }
              ]
            }
          }
        ],
        "resourceType": "Patient"
      }
    },
    {
      "fullUrl": "urn:uuid:f59af82d-aee6-48a8-a838-0622308fbb8f",
      "resource": {
        "id": "f59af82d-aee6-48a8-a838-0622308fbb8f",
        "meta": {
          "profile": [
            "http://standardhealthrecord.org/fhir/StructureDefinition/shr-actor-Organization"
          ]
        },
        "type": [
          {
            "coding": [
              {
                "system": "http://hl7.org/fhir/ValueSet/organization-type",
                "code": "prov",
                "display": "Healthcare Provider"
              }
            ],
            "text": "Healthcare Provider"
          }
        ],
        "name": "Synthetic Provider",
        "resourceType": "Organization"
      }
    },
    {
      "fullUrl": "urn:uuid:d00680bf-25dd-465b-afac-d39a010cca0e",
      "resource": {
        "id": "d00680bf-25dd-465b-afac-d39a010cca0e",
        "meta": {
          "profile": [
            "http://standardhealthrecord.org/fhir/StructureDefinition/shr-encounter-Encounter"
          ]
        },
        "status": "finished",
        "class": {
          "code": "outpatient"
        },
        "type": [
          {
            "coding": [
              {
                "system": "http://snomed.info/sct",
                "code": "170258001"
              }
            ],
            "text": "Outpatient Encounter"
          }
        ],
        "subject": {
          "reference": "urn:uuid:5b81597d-5c6a-47d5-aef1-450bedcb2fb1"
        },
        "period": {
          "start": "2011-06-04T22:56:16-04:00",
          "end": "2011-06-04T23:56:16-04:00"
        },
        "serviceProvider": {
          "reference": "urn:uuid:f59af82d-aee6-48a8-a838-0622308fbb8f"
        },
        "resourceType": "Encounter"
      }
    },
    {
      "fullUrl": "urn:uuid:8a671dd0-c28f-4cea-9d8d-d1c0a47b60da",
      "resource": {
        "id": "8a671dd0-c28f-4cea-9d8d-d1c0a47b60da",
        "meta": {
          "profile": [
            "http://standardhealthrecord.org/fhir/StructureDefinition/shr-observation-Observation",
            "http://standardhealthrecord.org/fhir/StructureDefinition/shr-vital-VitalSign",
            "http://standardhealthrecord.org/fhir/StructureDefinition/shr-vital-BodyHeight"
          ]
        },
        "status": "final",
        "category": [
          {
            "coding": [
              {
                "system": "http://hl7.org/fhir/observation-category",
                "code": "vital-signs"
              }
            ]
          }
        ],
        "code": {
          "coding": [
            {
              "system": "http://loinc.org",
              "code": "8302-2",
              "display": "Body Height"
            }
          ],
          "text": "Body Height"
        },
        "subject": {
          "reference": "urn:uuid:5b81597d-5c6a-47d5-aef1-450bedcb2fb1"
        },
        "context": {
          "reference": "urn:uuid:d00680bf-25dd-465b-afac-d39a010cca0e"
        },
        "effectiveDateTime": "2011-06-04T22:56:16-04:00",
        "issued": "2011-06-04T22:56:16-04:00",
        "valueQuantity": {
          "value": 172.8293824236065,
          "unit": "cm",
          "system": "http://unitsofmeasure.org/",
          "code": "cm"
        },
        "resourceType": "Observation"
      }
    },
    {
      "fullUrl": "urn:uuid:8ef7136d-6288-4e48-8759-b36628238c0c",
      "resource": {
        "id": "8ef7136d-6288-4e48-8759-b36628238c0c",
        "meta": {
          "profile": [
            "http://standardhealthrecord.org/fhir/StructureDefinition/shr-observation-Observation",
            "http://standardhealthrecord.org/fhir/StructureDefinition/shr-vital-VitalSign",
            "http://standardhealthrecord.org/fhir/StructureDefinition/shr-vital-BodyWeight"
          ]
        },
        "status": "final",
        "category": [
          {
            "coding": [
              {
                "system": "http://hl7.org/fhir/observation-category",
                "code": "vital-signs"
              }
            ]
          }
        ],
        "code": {
          "coding": [
            {
              "system": "http://loinc.org",
              "code": "29463-7",
              "display": "Body Weight"
            }
          ],
          "text": "Body Weight"
        },
        "subject": {
          "reference": "urn:uuid:5b81597d-5c6a-47d5-aef1-450bedcb2fb1"
        },
        "context": {
          "reference": "urn:uuid:d00680bf-25dd-465b-afac-d39a010cca0e"
        },
        "effectiveDateTime": "2011-06-04T22:56:16-04:00",
        "issued": "2011-06-04T22:56:16-04:00",
        "valueQuantity": {
          "value": 55.42660357620192,
          "unit": "kg",
          "system": "http://unitsofmeasure.org/",
          "code": "kg"
        },
        "resourceType": "Observation"
      }
    },
    {
      "fullUrl": "urn:uuid:6e845901-a628-4fb5-b5db-091dcac44d29",
      "resource": {
        "id": "6e845901-a628-4fb5-b5db-091dcac44d29",
        "meta": {
          "profile": [
            "http://standardhealthrecord.org/fhir/StructureDefinition/shr-observation-Observation",
            "http://standardhealthrecord.org/fhir/StructureDefinition/shr-vital-VitalSign",
            "http://standardhealthrecord.org/fhir/StructureDefinition/shr-vital-BodyMassIndex"
          ]
        },
        "status": "final",
        "category": [
          {
            "coding": [
              {
                "system": "http://hl7.org/fhir/observation-category",
                "code": "vital-signs"
              }
            ]
          }
        ],
        "code": {
          "coding": [
            {
              "system": "http://loinc.org",
              "code": "39156-5",
              "display": "Body Mass Index"
            }
          ],
          "text": "Body Mass Index"
        },
        "subject": {
          "reference": "urn:uuid:5b81597d-5c6a-47d5-aef1-450bedcb2fb1"
        },
        "context": {
          "reference": "urn:uuid:d00680bf-25dd-465b-afac-d39a010cca0e"
        },
        "effectiveDateTime": "2011-06-04T22:56:16-04:00",
        "issued": "2011-06-04T22:56:16-04:00",
        "valueQuantity": {
          "value": 18.555946454055512,
          "unit": "kg/m2",
          "system": "http://unitsofmeasure.org/",
          "code": "kg/m2"
        },
        "resourceType": "Observation"
      }
    },
    {
      "fullUrl": "urn:uuid:bf3d7a6e-4d9a-498d-b729-b2a027a8a2e0",
      "resource": {
        "id": "bf3d7a6e-4d9a-498d-b729-b2a027a8a2e0",
        "meta": {
          "profile": [
            "http://standardhealthrecord.org/fhir/StructureDefinition/shr-observation-Observation",
            "http://standardhealthrecord.org/fhir/StructureDefinition/shr-vital-BloodPressure"
          ]
        },
        "status": "final",
        "category": [
          {
            "coding": [
              {
                "system": "http://hl7.org/fhir/observation-category",
                "code": "vital-signs"
              }
            ]
          }
        ],
        "code": {
          "coding": [
            {
              "system": "http://loinc.org",
              "code": "55284-4",
              "display": "Blood Pressure"
            }
          ]
        },
        "subject": {
          "reference": "urn:uuid:5b81597d-5c6a-47d5-aef1-450bedcb2fb1"
        },
        "context": {
          "reference": "urn:uuid:d00680bf-25dd-465b-afac-d39a010cca0e"
        },
        "effectiveDateTime": "2011-06-04T22:56:16-04:00",
        "issued": "2011-06-04T22:56:16-04:00",
        "component": [
          {
            "code": {
              "coding": [
                {
                  "system": "http://loinc.org",
                  "code": "8480-6",
                  "display": "Systolic Blood Pressure"
                }
              ],
              "text": "Systolic Blood Pressure"
            },
            "valueQuantity": {
              "value": 118,
              "unit": "mmHg",
              "system": "http://unitsofmeasure.org/",
              "code": "mmHg"
            }
          },
          {
            "code": {
              "coding": [
                {
                  "system": "http://loinc.org",
                  "code": "8462-4",
                  "display": "Diastolic Blood Pressure"
                }
              ],
              "text": "Diastolic Blood Pressure"
            },
            "valueQuantity": {
              "value": 89,
              "unit": "mmHg",
              "system": "http://unitsofmeasure.org/",
              "code": "mmHg"
            }
          }
        ],
        "resourceType": "Observation"
      }
    },
    {
      "resource": {
        "meta": {
          "profile": [
            "http://standardhealthrecord.org/fhir/StructureDefinition/shr-immunization-Immunization"
          ]
        },
        "status": "completed",
        "notGiven": false,
        "vaccineCode": {
          "coding": [
            {
              "system": "http://hl7.org/fhir/sid/cvx",
              "code": "140",
              "display": "Influenza, seasonal, injectable, preservative free"
            }
          ],
          "text": "Influenza, seasonal, injectable, preservative free"
        },
        "patient": {
          "reference": "urn:uuid:5b81597d-5c6a-47d5-aef1-450bedcb2fb1"
        },
        "encounter": {
          "reference": "urn:uuid:d00680bf-25dd-465b-afac-d39a010cca0e"
        },
        "date": "2011-06-04T22:56:16-04:00",
        "primarySource": true,
        "resourceType": "Immunization"
      }
    },
    {
      "resource": {
        "meta": {
          "profile": [
            "http://standardhealthrecord.org/fhir/StructureDefinition/shr-immunization-Immunization"
          ]
        },
        "status": "completed",
        "notGiven": false,
        "vaccineCode": {
          "coding": [
            {
              "system": "http://hl7.org/fhir/sid/cvx",
              "code": "114",
              "display": "meningococcal MCV4P"
            }
          ],
          "text": "meningococcal MCV4P"
        },
        "patient": {
          "reference": "urn:uuid:5b81597d-5c6a-47d5-aef1-450bedcb2fb1"
        },
        "encounter": {
          "reference": "urn:uuid:d00680bf-25dd-465b-afac-d39a010cca0e"
        },
        "date": "2011-06-04T22:56:16-04:00",
        "primarySource": true,
        "resourceType": "Immunization"
      }
    },
    {
      "fullUrl": "urn:uuid:e82d0a9e-e555-4c35-9e61-481a4a192e4c",
      "resource": {
        "id": "e82d0a9e-e555-4c35-9e61-481a4a192e4c",
        "meta": {
          "profile": [
            "http://standardhealthrecord.org/fhir/StructureDefinition/shr-encounter-Encounter"
          ]
        },
        "status": "finished",
        "class": {
          "code": "outpatient"
        },
        "type": [
          {
            "coding": [
              {
                "system": "http://snomed.info/sct",
                "code": "170258001"
              }
            ],
            "text": "Outpatient Encounter"
          }
        ],
        "subject": {
          "reference": "urn:uuid:5b81597d-5c6a-47d5-aef1-450bedcb2fb1"
        },
        "period": {
          "start": "2012-06-09T09:40:10-04:00",
          "end": "2012-06-09T10:40:10-04:00"
        },
        "serviceProvider": {
          "reference": "urn:uuid:f59af82d-aee6-48a8-a838-0622308fbb8f"
        },
        "resourceType": "Encounter"
      }
    },
    {
      "fullUrl": "urn:uuid:303362d2-c229-4cbc-8acd-0b73f2379ea6",
      "resource": {
        "id": "303362d2-c229-4cbc-8acd-0b73f2379ea6",
        "meta": {
          "profile": [
            "http://standardhealthrecord.org/fhir/StructureDefinition/shr-observation-Observation",
            "http://standardhealthrecord.org/fhir/StructureDefinition/shr-vital-VitalSign",
            "http://standardhealthrecord.org/fhir/StructureDefinition/shr-vital-BodyHeight"
          ]
        },
        "status": "final",
        "category": [
          {
            "coding": [
              {
                "system": "http://hl7.org/fhir/observation-category",
                "code": "vital-signs"
              }
            ]
          }
        ],
        "code": {
          "coding": [
            {
              "system": "http://loinc.org",
              "code": "8302-2",
              "display": "Body Height"
            }
          ],
          "text": "Body Height"
        },
        "subject": {
          "reference": "urn:uuid:5b81597d-5c6a-47d5-aef1-450bedcb2fb1"
        },
        "context": {
          "reference": "urn:uuid:e82d0a9e-e555-4c35-9e61-481a4a192e4c"
        },
        "effectiveDateTime": "2012-06-09T09:40:10-04:00",
        "issued": "2012-06-09T09:40:10-04:00",
        "valueQuantity": {
          "value": 174.14490029341195,
          "unit": "cm",
          "system": "http://unitsofmeasure.org/",
          "code": "cm"
        },
        "resourceType": "Observation"
      }
    },
    {
      "fullUrl": "urn:uuid:b71e2a69-35c2-4271-ac83-4d8931f4940b",
      "resource": {
        "id": "b71e2a69-35c2-4271-ac83-4d8931f4940b",
        "meta": {
          "profile": [
            "http://standardhealthrecord.org/fhir/StructureDefinition/shr-observation-Observation",
            "http://standardhealthrecord.org/fhir/StructureDefinition/shr-vital-VitalSign",
            "http://standardhealthrecord.org/fhir/StructureDefinition/shr-vital-BodyWeight"
          ]
        },
        "status": "final",
        "category": [
          {
            "coding": [
              {
                "system": "http://hl7.org/fhir/observation-category",
                "code": "vital-signs"
              }
            ]
          }
        ],
        "code": {
          "coding": [
            {
              "system": "http://loinc.org",
              "code": "29463-7",
              "display": "Body Weight"
            }
          ],
          "text": "Body Weight"
        },
        "subject": {
          "reference": "urn:uuid:5b81597d-5c6a-47d5-aef1-450bedcb2fb1"
        },
        "context": {
          "reference": "urn:uuid:e82d0a9e-e555-4c35-9e61-481a4a192e4c"
        },
        "effectiveDateTime": "2012-06-09T09:40:10-04:00",
        "issued": "2012-06-09T09:40:10-04:00",
        "valueQuantity": {
          "value": 58.615176054898704,
          "unit": "kg",
          "system": "http://unitsofmeasure.org/",
          "code": "kg"
        },
        "resourceType": "Observation"
      }
    },
    {
      "fullUrl": "urn:uuid:ac50a23f-ce6b-4bed-9526-2fc8c59d93f8",
      "resource": {
        "id": "ac50a23f-ce6b-4bed-9526-2fc8c59d93f8",
        "meta": {
          "profile": [
            "http://standardhealthrecord.org/fhir/StructureDefinition/shr-observation-Observation",
            "http://standardhealthrecord.org/fhir/StructureDefinition/shr-vital-VitalSign",
            "http://standardhealthrecord.org/fhir/StructureDefinition/shr-vital-BodyMassIndex"
          ]
        },
        "status": "final",
        "category": [
          {
            "coding": [
              {
                "system": "http://hl7.org/fhir/observation-category",
                "code": "vital-signs"
              }
            ]
          }
        ],
        "code": {
          "coding": [
            {
              "system": "http://loinc.org",
              "code": "39156-5",
              "display": "Body Mass Index"
            }
          ],
          "text": "Body Mass Index"
        },
        "subject": {
          "reference": "urn:uuid:5b81597d-5c6a-47d5-aef1-450bedcb2fb1"
        },
        "context": {
          "reference": "urn:uuid:e82d0a9e-e555-4c35-9e61-481a4a192e4c"
        },
        "effectiveDateTime": "2012-06-09T09:40:10-04:00",
        "issued": "2012-06-09T09:40:10-04:00",
        "valueQuantity": {
          "value": 19.328072758189656,
          "unit": "kg/m2",
          "system": "http://unitsofmeasure.org/",
          "code": "kg/m2"
        },
        "resourceType": "Observation"
      }
    },
    {
      "fullUrl": "urn:uuid:bbb1336f-f2ad-4158-8b82-b2102628f289",
      "resource": {
        "id": "bbb1336f-f2ad-4158-8b82-b2102628f289",
        "meta": {
          "profile": [
            "http://standardhealthrecord.org/fhir/StructureDefinition/shr-observation-Observation",
            "http://standardhealthrecord.org/fhir/StructureDefinition/shr-vital-BloodPressure"
          ]
        },
        "status": "final",
        "category": [
          {
            "coding": [
              {
                "system": "http://hl7.org/fhir/observation-category",
                "code": "vital-signs"
              }
            ]
          }
        ],
        "code": {
          "coding": [
            {
              "system": "http://loinc.org",
              "code": "55284-4",
              "display": "Blood Pressure"
            }
          ]
        },
        "subject": {
          "reference": "urn:uuid:5b81597d-5c6a-47d5-aef1-450bedcb2fb1"
        },
        "context": {
          "reference": "urn:uuid:e82d0a9e-e555-4c35-9e61-481a4a192e4c"
        },
        "effectiveDateTime": "2012-06-09T09:40:10-04:00",
        "issued": "2012-06-09T09:40:10-04:00",
        "component": [
          {
            "code": {
              "coding": [
                {
                  "system": "http://loinc.org",
                  "code": "8480-6",
                  "display": "Systolic Blood Pressure"
                }
              ],
              "text": "Systolic Blood Pressure"
            },
            "valueQuantity": {
              "value": 135,
              "unit": "mmHg",
              "system": "http://unitsofmeasure.org/",
              "code": "mmHg"
            }
          },
          {
            "code": {
              "coding": [
                {
                  "system": "http://loinc.org",
                  "code": "8462-4",
                  "display": "Diastolic Blood Pressure"
                }
              ],
              "text": "Diastolic Blood Pressure"
            },
            "valueQuantity": {
              "value": 85,
              "unit": "mmHg",
              "system": "http://unitsofmeasure.org/",
              "code": "mmHg"
            }
          }
        ],
        "resourceType": "Observation"
      }
    },
    {
      "resource": {
        "meta": {
          "profile": [
            "http://standardhealthrecord.org/fhir/StructureDefinition/shr-procedure-Procedure"
          ]
        },
        "extension": [
          {
            "url": "http://standardhealthrecord.org/fhir/StructureDefinition/shr-core-CodeableConcept-extension",
            "valueCodeableConcept": {
              "coding": [
                {
                  "system": "http://snomed.info/sct",
                  "code": "428191000124101",
                  "display": "Documentation of current medications"
                }
              ],
              "text": "Documentation of current medications"
            }
          }
        ],
        "status": "completed",
        "code": {
          "coding": [
            {
              "system": "http://snomed.info/sct",
              "code": "428191000124101",
              "display": "Documentation of current medications"
            }
          ],
          "text": "Documentation of current medications"
        },
        "subject": {
          "reference": "urn:uuid:5b81597d-5c6a-47d5-aef1-450bedcb2fb1"
        },
        "context": {
          "reference": "urn:uuid:e82d0a9e-e555-4c35-9e61-481a4a192e4c"
        },
        "performedDateTime": "2012-06-09T09:40:10-04:00",
        "resourceType": "Procedure"
      }
    },
    {
      "resource": {
        "meta": {
          "profile": [
            "http://standardhealthrecord.org/fhir/StructureDefinition/shr-immunization-Immunization"
          ]
        },
        "status": "completed",
        "notGiven": false,
        "vaccineCode": {
          "coding": [
            {
              "system": "http://hl7.org/fhir/sid/cvx",
              "code": "140",
              "display": "Influenza, seasonal, injectable, preservative free"
            }
          ],
          "text": "Influenza, seasonal, injectable, preservative free"
        },
        "patient": {
          "reference": "urn:uuid:5b81597d-5c6a-47d5-aef1-450bedcb2fb1"
        },
        "encounter": {
          "reference": "urn:uuid:e82d0a9e-e555-4c35-9e61-481a4a192e4c"
        },
        "date": "2012-06-09T09:40:10-04:00",
        "primarySource": true,
        "resourceType": "Immunization"
      }
    },
    {
      "fullUrl": "urn:uuid:633f8054-b267-4834-85c4-ab14d63a1259",
      "resource": {
        "id": "633f8054-b267-4834-85c4-ab14d63a1259",
        "meta": {
          "profile": [
            "http://standardhealthrecord.org/fhir/StructureDefinition/shr-encounter-Encounter"
          ]
        },
        "status": "finished",
        "class": {
          "code": "outpatient"
        },
        "type": [
          {
            "coding": [
              {
                "system": "http://snomed.info/sct",
                "code": "185349003"
              }
            ],
            "text": "Outpatient Encounter"
          }
        ],
        "subject": {
          "reference": "urn:uuid:5b81597d-5c6a-47d5-aef1-450bedcb2fb1"
        },
        "period": {
          "start": "2013-06-27T18:00:09-04:00",
          "end": "2013-06-27T19:00:09-04:00"
        },
        "serviceProvider": {
          "reference": "urn:uuid:f59af82d-aee6-48a8-a838-0622308fbb8f"
        },
        "resourceType": "Encounter"
      }
    },
    {
      "fullUrl": "urn:uuid:2df5a293-2048-4fe7-95ce-afec8f13b58b",
      "resource": {
        "id": "2df5a293-2048-4fe7-95ce-afec8f13b58b",
        "meta": {
          "profile": [
            "http://standardhealthrecord.org/fhir/StructureDefinition/shr-observation-Observation",
            "http://standardhealthrecord.org/fhir/StructureDefinition/shr-vital-VitalSign",
            "http://standardhealthrecord.org/fhir/StructureDefinition/shr-vital-BodyHeight"
          ]
        },
        "status": "final",
        "category": [
          {
            "coding": [
              {
                "system": "http://hl7.org/fhir/observation-category",
                "code": "vital-signs"
              }
            ]
          }
        ],
        "code": {
          "coding": [
            {
              "system": "http://loinc.org",
              "code": "8302-2",
              "display": "Body Height"
            }
          ],
          "text": "Body Height"
        },
        "subject": {
          "reference": "urn:uuid:5b81597d-5c6a-47d5-aef1-450bedcb2fb1"
        },
        "context": {
          "reference": "urn:uuid:633f8054-b267-4834-85c4-ab14d63a1259"
        },
        "effectiveDateTime": "2013-06-27T18:00:09-04:00",
        "issued": "2013-06-27T18:00:09-04:00",
        "valueQuantity": {
          "value": 174.72642554484935,
          "unit": "cm",
          "system": "http://unitsofmeasure.org/",
          "code": "cm"
        },
        "resourceType": "Observation"
      }
    },
    {
      "fullUrl": "urn:uuid:f1e38d31-ae64-4422-944a-212d5267ee25",
      "resource": {
        "id": "f1e38d31-ae64-4422-944a-212d5267ee25",
        "meta": {
          "profile": [
            "http://standardhealthrecord.org/fhir/StructureDefinition/shr-observation-Observation",
            "http://standardhealthrecord.org/fhir/StructureDefinition/shr-vital-VitalSign",
            "http://standardhealthrecord.org/fhir/StructureDefinition/shr-vital-BodyWeight"
          ]
        },
        "status": "final",
        "category": [
          {
            "coding": [
              {
                "system": "http://hl7.org/fhir/observation-category",
                "code": "vital-signs"
              }
            ]
          }
        ],
        "code": {
          "coding": [
            {
              "system": "http://loinc.org",
              "code": "29463-7",
              "display": "Body Weight"
            }
          ],
          "text": "Body Weight"
        },
        "subject": {
          "reference": "urn:uuid:5b81597d-5c6a-47d5-aef1-450bedcb2fb1"
        },
        "context": {
          "reference": "urn:uuid:633f8054-b267-4834-85c4-ab14d63a1259"
        },
        "effectiveDateTime": "2013-06-27T18:00:09-04:00",
        "issued": "2013-06-27T18:00:09-04:00",
        "valueQuantity": {
          "value": 60.614017867868796,
          "unit": "kg",
          "system": "http://unitsofmeasure.org/",
          "code": "kg"
        },
        "resourceType": "Observation"
      }
    },
    {
      "fullUrl": "urn:uuid:f14e2245-db5d-4667-a84b-fa3ee35cc5e4",
      "resource": {
        "id": "f14e2245-db5d-4667-a84b-fa3ee35cc5e4",
        "meta": {
          "profile": [
            "http://standardhealthrecord.org/fhir/StructureDefinition/shr-observation-Observation",
            "http://standardhealthrecord.org/fhir/StructureDefinition/shr-vital-VitalSign",
            "http://standardhealthrecord.org/fhir/StructureDefinition/shr-vital-BodyMassIndex"
          ]
        },
        "status": "final",
        "category": [
          {
            "coding": [
              {
                "system": "http://hl7.org/fhir/observation-category",
                "code": "vital-signs"
              }
            ]
          }
        ],
        "code": {
          "coding": [
            {
              "system": "http://loinc.org",
              "code": "39156-5",
              "display": "Body Mass Index"
            }
          ],
          "text": "Body Mass Index"
        },
        "subject": {
          "reference": "urn:uuid:5b81597d-5c6a-47d5-aef1-450bedcb2fb1"
        },
        "context": {
          "reference": "urn:uuid:633f8054-b267-4834-85c4-ab14d63a1259"
        },
        "effectiveDateTime": "2013-06-27T18:00:09-04:00",
        "issued": "2013-06-27T18:00:09-04:00",
        "valueQuantity": {
          "value": 19.854359794327166,
          "unit": "kg/m2",
          "system": "http://unitsofmeasure.org/",
          "code": "kg/m2"
        },
        "resourceType": "Observation"
      }
    },
    {
      "fullUrl": "urn:uuid:3440a0aa-7c66-46f8-8fb5-49c9082f944b",
      "resource": {
        "id": "3440a0aa-7c66-46f8-8fb5-49c9082f944b",
        "meta": {
          "profile": [
            "http://standardhealthrecord.org/fhir/StructureDefinition/shr-observation-Observation",
            "http://standardhealthrecord.org/fhir/StructureDefinition/shr-vital-BloodPressure"
          ]
        },
        "status": "final",
        "category": [
          {
            "coding": [
              {
                "system": "http://hl7.org/fhir/observation-category",
                "code": "vital-signs"
              }
            ]
          }
        ],
        "code": {
          "coding": [
            {
              "system": "http://loinc.org",
              "code": "55284-4",
              "display": "Blood Pressure"
            }
          ]
        },
        "subject": {
          "reference": "urn:uuid:5b81597d-5c6a-47d5-aef1-450bedcb2fb1"
        },
        "context": {
          "reference": "urn:uuid:633f8054-b267-4834-85c4-ab14d63a1259"
        },
        "effectiveDateTime": "2013-06-27T18:00:09-04:00",
        "issued": "2013-06-27T18:00:09-04:00",
        "component": [
          {
            "code": {
              "coding": [
                {
                  "system": "http://loinc.org",
                  "code": "8480-6",
                  "display": "Systolic Blood Pressure"
                }
              ],
              "text": "Systolic Blood Pressure"
            },
            "valueQuantity": {
              "value": 110,
              "unit": "mmHg",
              "system": "http://unitsofmeasure.org/",
              "code": "mmHg"
            }
          },
          {
            "code": {
              "coding": [
                {
                  "system": "http://loinc.org",
                  "code": "8462-4",
                  "display": "Diastolic Blood Pressure"
                }
              ],
              "text": "Diastolic Blood Pressure"
            },
            "valueQuantity": {
              "value": 85,
              "unit": "mmHg",
              "system": "http://unitsofmeasure.org/",
              "code": "mmHg"
            }
          }
        ],
        "resourceType": "Observation"
      }
    },
    {
      "resource": {
        "meta": {
          "profile": [
            "http://standardhealthrecord.org/fhir/StructureDefinition/shr-procedure-Procedure"
          ]
        },
        "extension": [
          {
            "url": "http://standardhealthrecord.org/fhir/StructureDefinition/shr-core-CodeableConcept-extension",
            "valueCodeableConcept": {
              "coding": [
                {
                  "system": "http://snomed.info/sct",
                  "code": "428191000124101",
                  "display": "Documentation of current medications"
                }
              ],
              "text": "Documentation of current medications"
            }
          }
        ],
        "status": "completed",
        "code": {
          "coding": [
            {
              "system": "http://snomed.info/sct",
              "code": "428191000124101",
              "display": "Documentation of current medications"
            }
          ],
          "text": "Documentation of current medications"
        },
        "subject": {
          "reference": "urn:uuid:5b81597d-5c6a-47d5-aef1-450bedcb2fb1"
        },
        "context": {
          "reference": "urn:uuid:633f8054-b267-4834-85c4-ab14d63a1259"
        },
        "performedDateTime": "2013-06-27T18:00:09-04:00",
        "resourceType": "Procedure"
      }
    },
    {
      "resource": {
        "meta": {
          "profile": [
            "http://standardhealthrecord.org/fhir/StructureDefinition/shr-immunization-Immunization"
          ]
        },
        "status": "completed",
        "notGiven": false,
        "vaccineCode": {
          "coding": [
            {
              "system": "http://hl7.org/fhir/sid/cvx",
              "code": "140",
              "display": "Influenza, seasonal, injectable, preservative free"
            }
          ],
          "text": "Influenza, seasonal, injectable, preservative free"
        },
        "patient": {
          "reference": "urn:uuid:5b81597d-5c6a-47d5-aef1-450bedcb2fb1"
        },
        "encounter": {
          "reference": "urn:uuid:633f8054-b267-4834-85c4-ab14d63a1259"
        },
        "date": "2013-06-27T18:00:09-04:00",
        "primarySource": true,
        "resourceType": "Immunization"
      }
    },
    {
      "fullUrl": "urn:uuid:c8464b85-deb2-40bf-9109-c2657e7522fc",
      "resource": {
        "id": "c8464b85-deb2-40bf-9109-c2657e7522fc",
        "meta": {
          "profile": [
            "http://standardhealthrecord.org/fhir/StructureDefinition/shr-encounter-Encounter"
          ]
        },
        "status": "finished",
        "class": {
          "code": "ambulatory"
        },
        "type": [
          {
            "coding": [
              {
                "system": "http://snomed.info/sct",
                "code": "185345009"
              }
            ],
            "text": "Encounter for symptom"
          }
        ],
        "subject": {
          "reference": "urn:uuid:5b81597d-5c6a-47d5-aef1-450bedcb2fb1"
        },
        "period": {
          "start": "2013-09-12T04:07:15-04:00",
          "end": "2013-09-12T04:07:15-04:00"
        },
        "reason": {
          "coding": [
            {
              "system": "http://snomed.info/sct",
              "code": "10509002",
              "display": "Acute bronchitis (disorder)"
            }
          ]
        },
        "serviceProvider": {
          "reference": "urn:uuid:f59af82d-aee6-48a8-a838-0622308fbb8f"
        },
        "resourceType": "Encounter"
      }
    },
    {
      "fullUrl": "urn:uuid:fb317338-ae4e-467b-8d76-e608d1b28894",
      "resource": {
        "id": "fb317338-ae4e-467b-8d76-e608d1b28894",
        "meta": {
          "profile": [
            "http://standardhealthrecord.org/fhir/StructureDefinition/shr-problem-Problem"
          ]
        },
        "clinicalStatus": "active",
        "verificationStatus": "confirmed",
        "code": {
          "coding": [
            {
              "system": "http://snomed.info/sct",
              "code": "10509002",
              "display": "Acute bronchitis (disorder)"
            }
          ],
          "text": "Acute bronchitis (disorder)"
        },
        "subject": {
          "reference": "urn:uuid:5b81597d-5c6a-47d5-aef1-450bedcb2fb1"
        },
        "context": {
          "reference": "urn:uuid:c8464b85-deb2-40bf-9109-c2657e7522fc"
        },
        "onsetDateTime": "2013-09-12T04:07:15-04:00",
        "abatementDateTime": "2013-09-29T17:16:46-04:00",
        "assertedDate": "2013-09-12",
        "resourceType": "Condition"
      }
    },
    {
      "resource": {
        "status": "completed",
        "category": [
          {
            "coding": [
              {
                "system": "http://snomed.info/sct",
                "code": "53950000",
                "display": "Respiratory therapy"
              }
            ]
          }
        ],
        "subject": {
          "reference": "urn:uuid:5b81597d-5c6a-47d5-aef1-450bedcb2fb1"
        },
        "context": {
          "reference": "urn:uuid:c8464b85-deb2-40bf-9109-c2657e7522fc"
        },
        "period": {
          "start": "2013-09-12",
          "end": "2014-07-06"
        },
        "addresses": [
          {
            "reference": "urn:uuid:fb317338-ae4e-467b-8d76-e608d1b28894"
          }
        ],
        "activity": [
          {
            "detail": {
              "code": {
                "coding": [
                  {
                    "system": "http://snomed.info/sct",
                    "code": "304510005",
                    "display": "Recommendation to avoid exercise"
                  }
                ]
              },
              "status": "completed"
            }
          },
          {
            "detail": {
              "code": {
                "coding": [
                  {
                    "system": "http://snomed.info/sct",
                    "code": "371605008",
                    "display": "Deep breathing and coughing exercises"
                  }
                ]
              },
              "status": "completed"
            }
          }
        ],
        "resourceType": "CarePlan"
      }
    },
    {
      "resource": {
        "meta": {
          "profile": [
            "http://standardhealthrecord.org/fhir/StructureDefinition/shr-medication-Medication"
          ]
        },
        "code": {
          "coding": [
            {
              "system": "http://www.nlm.nih.gov/research/umls/rxnorm",
              "code": "608680",
              "display": "Acetaminophen 160 MG"
            }
          ],
          "text": "Acetaminophen 160 MG"
        },
        "resourceType": "Medication"
      }
    },
    {
      "resource": {
        "meta": {
          "profile": [
            "http://standardhealthrecord.org/fhir/StructureDefinition/shr-medication-MedicationPrescription"
          ]
        },
        "extension": [
          {
            "url": "http://standardhealthrecord.org/fhir/StructureDefinition/shr-base-ActionCode-extension",
            "valueCodeableConcept": {
              "coding": [
                {
                  "system": "http://snomed.info/sct",
                  "code": "33633005",
                  "display": "Prescription of drug (procedure)"
                }
              ],
              "text": "Prescription of drug (procedure)"
            }
          }
        ],
        "status": "stopped",
        "medicationReference": {
          "reference": ""
        },
        "subject": {
          "reference": "urn:uuid:5b81597d-5c6a-47d5-aef1-450bedcb2fb1"
        },
        "context": {
          "reference": "urn:uuid:c8464b85-deb2-40bf-9109-c2657e7522fc"
        },
        "authoredOn": "2013-09-12",
        "reasonReference": [
          {
            "reference": "urn:uuid:fb317338-ae4e-467b-8d76-e608d1b28894"
          }
        ],
        "dosageInstruction": [
          {

          }
        ],
        "resourceType": "MedicationRequest"
      }
    },
    {
      "fullUrl": "urn:uuid:c3d4b1a1-3b93-4c84-87d1-9e5ee4c674aa",
      "resource": {
        "id": "c3d4b1a1-3b93-4c84-87d1-9e5ee4c674aa",
        "meta": {
          "profile": [
            "http://standardhealthrecord.org/fhir/StructureDefinition/shr-encounter-Encounter"
          ]
        },
        "status": "finished",
        "class": {
          "code": "ambulatory"
        },
        "type": [
          {
            "coding": [
              {
                "system": "http://snomed.info/sct",
                "code": "185345009"
              }
            ],
            "text": "Encounter for symptom"
          }
        ],
        "subject": {
          "reference": "urn:uuid:5b81597d-5c6a-47d5-aef1-450bedcb2fb1"
        },
        "period": {
          "start": "2014-01-14T23:43:58-05:00",
          "end": "2014-01-14T23:43:58-05:00"
        },
        "reason": {
          "coding": [
            {
              "system": "http://snomed.info/sct",
              "code": "195662009",
              "display": "Acute viral pharyngitis (disorder)"
            }
          ]
        },
        "serviceProvider": {
          "reference": "urn:uuid:f59af82d-aee6-48a8-a838-0622308fbb8f"
        },
        "resourceType": "Encounter"
      }
    },
    {
      "fullUrl": "urn:uuid:fdbd6870-8e76-42d8-b3c9-6bdf04489879",
      "resource": {
        "id": "fdbd6870-8e76-42d8-b3c9-6bdf04489879",
        "meta": {
          "profile": [
            "http://standardhealthrecord.org/fhir/StructureDefinition/shr-problem-Problem"
          ]
        },
        "clinicalStatus": "active",
        "verificationStatus": "confirmed",
        "code": {
          "coding": [
            {
              "system": "http://snomed.info/sct",
              "code": "195662009",
              "display": "Acute viral pharyngitis (disorder)"
            }
          ],
          "text": "Acute viral pharyngitis (disorder)"
        },
        "subject": {
          "reference": "urn:uuid:5b81597d-5c6a-47d5-aef1-450bedcb2fb1"
        },
        "context": {
          "reference": "urn:uuid:c3d4b1a1-3b93-4c84-87d1-9e5ee4c674aa"
        },
        "onsetDateTime": "2014-01-14T23:43:58-05:00",
        "abatementDateTime": "2014-01-23T08:25:23-05:00",
        "assertedDate": "2014-01-14",
        "resourceType": "Condition"
      }
    },
    {
      "fullUrl": "urn:uuid:f76e4db1-2968-451b-87a7-86efd005b467",
      "resource": {
        "id": "f76e4db1-2968-451b-87a7-86efd005b467",
        "meta": {
          "profile": [
            "http://standardhealthrecord.org/fhir/StructureDefinition/shr-observation-Observation",
            "http://standardhealthrecord.org/fhir/StructureDefinition/shr-vital-VitalSign"
          ]
        },
        "status": "final",
        "category": [
          {
            "coding": [
              {
                "system": "http://hl7.org/fhir/observation-category",
                "code": "vital-signs"
              }
            ]
          }
        ],
        "code": {
          "coding": [
            {
              "system": "http://loinc.org",
              "code": "8331-1",
              "display": "Oral temperature"
            }
          ],
          "text": "Oral temperature"
        },
        "subject": {
          "reference": "urn:uuid:5b81597d-5c6a-47d5-aef1-450bedcb2fb1"
        },
        "context": {
          "reference": "urn:uuid:c3d4b1a1-3b93-4c84-87d1-9e5ee4c674aa"
        },
        "effectiveDateTime": "2014-01-14T23:43:58-05:00",
        "issued": "2014-01-14T23:43:58-05:00",
        "valueQuantity": {
          "value": 37,
          "unit": "Cel",
          "system": "http://unitsofmeasure.org/",
          "code": "Cel"
        },
        "resourceType": "Observation"
      }
    },
    {
      "fullUrl": "urn:uuid:f7c2b92d-2f4a-4490-99c5-c7f1e095f220",
      "resource": {
        "id": "f7c2b92d-2f4a-4490-99c5-c7f1e095f220",
        "meta": {
          "profile": [
            "http://standardhealthrecord.org/fhir/StructureDefinition/shr-encounter-Encounter"
          ]
        },
        "status": "finished",
        "class": {
          "code": "outpatient"
        },
        "type": [
          {
            "coding": [
              {
                "system": "http://snomed.info/sct",
                "code": "185349003"
              }
            ],
            "text": "Outpatient Encounter"
          }
        ],
        "subject": {
          "reference": "urn:uuid:5b81597d-5c6a-47d5-aef1-450bedcb2fb1"
        },
        "period": {
          "start": "2014-07-06T13:01:59-04:00",
          "end": "2014-07-06T14:01:59-04:00"
        },
        "serviceProvider": {
          "reference": "urn:uuid:f59af82d-aee6-48a8-a838-0622308fbb8f"
        },
        "resourceType": "Encounter"
      }
    },
    {
      "fullUrl": "urn:uuid:0fbb46b0-8996-4749-a781-57bd9182b184",
      "resource": {
        "id": "0fbb46b0-8996-4749-a781-57bd9182b184",
        "meta": {
          "profile": [
            "http://standardhealthrecord.org/fhir/StructureDefinition/shr-observation-Observation",
            "http://standardhealthrecord.org/fhir/StructureDefinition/shr-vital-VitalSign",
            "http://standardhealthrecord.org/fhir/StructureDefinition/shr-vital-BodyHeight"
          ]
        },
        "status": "final",
        "category": [
          {
            "coding": [
              {
                "system": "http://hl7.org/fhir/observation-category",
                "code": "vital-signs"
              }
            ]
          }
        ],
        "code": {
          "coding": [
            {
              "system": "http://loinc.org",
              "code": "8302-2",
              "display": "Body Height"
            }
          ],
          "text": "Body Height"
        },
        "subject": {
          "reference": "urn:uuid:5b81597d-5c6a-47d5-aef1-450bedcb2fb1"
        },
        "context": {
          "reference": "urn:uuid:f7c2b92d-2f4a-4490-99c5-c7f1e095f220"
        },
        "effectiveDateTime": "2014-07-06T13:01:59-04:00",
        "issued": "2014-07-06T13:01:59-04:00",
        "valueQuantity": {
          "value": 175.03160351896304,
          "unit": "cm",
          "system": "http://unitsofmeasure.org/",
          "code": "cm"
        },
        "resourceType": "Observation"
      }
    },
    {
      "fullUrl": "urn:uuid:d476c61f-eca9-40e7-b854-b0d0ba7296cb",
      "resource": {
        "id": "d476c61f-eca9-40e7-b854-b0d0ba7296cb",
        "meta": {
          "profile": [
            "http://standardhealthrecord.org/fhir/StructureDefinition/shr-observation-Observation",
            "http://standardhealthrecord.org/fhir/StructureDefinition/shr-vital-VitalSign",
            "http://standardhealthrecord.org/fhir/StructureDefinition/shr-vital-BodyWeight"
          ]
        },
        "status": "final",
        "category": [
          {
            "coding": [
              {
                "system": "http://hl7.org/fhir/observation-category",
                "code": "vital-signs"
              }
            ]
          }
        ],
        "code": {
          "coding": [
            {
              "system": "http://loinc.org",
              "code": "29463-7",
              "display": "Body Weight"
            }
          ],
          "text": "Body Weight"
        },
        "subject": {
          "reference": "urn:uuid:5b81597d-5c6a-47d5-aef1-450bedcb2fb1"
        },
        "context": {
          "reference": "urn:uuid:f7c2b92d-2f4a-4490-99c5-c7f1e095f220"
        },
        "effectiveDateTime": "2014-07-06T13:01:59-04:00",
        "issued": "2014-07-06T13:01:59-04:00",
        "valueQuantity": {
          "value": 62.070216117411476,
          "unit": "kg",
          "system": "http://unitsofmeasure.org/",
          "code": "kg"
        },
        "resourceType": "Observation"
      }
    },
    {
      "fullUrl": "urn:uuid:a9e0dfbf-4050-4b4f-8e43-2e0325f45b31",
      "resource": {
        "id": "a9e0dfbf-4050-4b4f-8e43-2e0325f45b31",
        "meta": {
          "profile": [
            "http://standardhealthrecord.org/fhir/StructureDefinition/shr-observation-Observation",
            "http://standardhealthrecord.org/fhir/StructureDefinition/shr-vital-VitalSign",
            "http://standardhealthrecord.org/fhir/StructureDefinition/shr-vital-BodyMassIndex"
          ]
        },
        "status": "final",
        "category": [
          {
            "coding": [
              {
                "system": "http://hl7.org/fhir/observation-category",
                "code": "vital-signs"
              }
            ]
          }
        ],
        "code": {
          "coding": [
            {
              "system": "http://loinc.org",
              "code": "39156-5",
              "display": "Body Mass Index"
            }
          ],
          "text": "Body Mass Index"
        },
        "subject": {
          "reference": "urn:uuid:5b81597d-5c6a-47d5-aef1-450bedcb2fb1"
        },
        "context": {
          "reference": "urn:uuid:f7c2b92d-2f4a-4490-99c5-c7f1e095f220"
        },
        "effectiveDateTime": "2014-07-06T13:01:59-04:00",
        "issued": "2014-07-06T13:01:59-04:00",
        "valueQuantity": {
          "value": 20.260507257939985,
          "unit": "kg/m2",
          "system": "http://unitsofmeasure.org/",
          "code": "kg/m2"
        },
        "resourceType": "Observation"
      }
    },
    {
      "fullUrl": "urn:uuid:fb313703-e7ba-45c4-a25b-8691b50de202",
      "resource": {
        "id": "fb313703-e7ba-45c4-a25b-8691b50de202",
        "meta": {
          "profile": [
            "http://standardhealthrecord.org/fhir/StructureDefinition/shr-observation-Observation",
            "http://standardhealthrecord.org/fhir/StructureDefinition/shr-vital-BloodPressure"
          ]
        },
        "status": "final",
        "category": [
          {
            "coding": [
              {
                "system": "http://hl7.org/fhir/observation-category",
                "code": "vital-signs"
              }
            ]
          }
        ],
        "code": {
          "coding": [
            {
              "system": "http://loinc.org",
              "code": "55284-4",
              "display": "Blood Pressure"
            }
          ]
        },
        "subject": {
          "reference": "urn:uuid:5b81597d-5c6a-47d5-aef1-450bedcb2fb1"
        },
        "context": {
          "reference": "urn:uuid:f7c2b92d-2f4a-4490-99c5-c7f1e095f220"
        },
        "effectiveDateTime": "2014-07-06T13:01:59-04:00",
        "issued": "2014-07-06T13:01:59-04:00",
        "component": [
          {
            "code": {
              "coding": [
                {
                  "system": "http://loinc.org",
                  "code": "8480-6",
                  "display": "Systolic Blood Pressure"
                }
              ],
              "text": "Systolic Blood Pressure"
            },
            "valueQuantity": {
              "value": 100,
              "unit": "mmHg",
              "system": "http://unitsofmeasure.org/",
              "code": "mmHg"
            }
          },
          {
            "code": {
              "coding": [
                {
                  "system": "http://loinc.org",
                  "code": "8462-4",
                  "display": "Diastolic Blood Pressure"
                }
              ],
              "text": "Diastolic Blood Pressure"
            },
            "valueQuantity": {
              "value": 77,
              "unit": "mmHg",
              "system": "http://unitsofmeasure.org/",
              "code": "mmHg"
            }
          }
        ],
        "resourceType": "Observation"
      }
    },
    {
      "resource": {
        "meta": {
          "profile": [
            "http://standardhealthrecord.org/fhir/StructureDefinition/shr-procedure-Procedure"
          ]
        },
        "extension": [
          {
            "url": "http://standardhealthrecord.org/fhir/StructureDefinition/shr-core-CodeableConcept-extension",
            "valueCodeableConcept": {
              "coding": [
                {
                  "system": "http://snomed.info/sct",
                  "code": "428191000124101",
                  "display": "Documentation of current medications"
                }
              ],
              "text": "Documentation of current medications"
            }
          }
        ],
        "status": "completed",
        "code": {
          "coding": [
            {
              "system": "http://snomed.info/sct",
              "code": "428191000124101",
              "display": "Documentation of current medications"
            }
          ],
          "text": "Documentation of current medications"
        },
        "subject": {
          "reference": "urn:uuid:5b81597d-5c6a-47d5-aef1-450bedcb2fb1"
        },
        "context": {
          "reference": "urn:uuid:f7c2b92d-2f4a-4490-99c5-c7f1e095f220"
        },
        "performedDateTime": "2014-07-06T13:01:59-04:00",
        "resourceType": "Procedure"
      }
    },
    {
      "resource": {
        "meta": {
          "profile": [
            "http://standardhealthrecord.org/fhir/StructureDefinition/shr-immunization-Immunization"
          ]
        },
        "status": "completed",
        "notGiven": false,
        "vaccineCode": {
          "coding": [
            {
              "system": "http://hl7.org/fhir/sid/cvx",
              "code": "140",
              "display": "Influenza, seasonal, injectable, preservative free"
            }
          ],
          "text": "Influenza, seasonal, injectable, preservative free"
        },
        "patient": {
          "reference": "urn:uuid:5b81597d-5c6a-47d5-aef1-450bedcb2fb1"
        },
        "encounter": {
          "reference": "urn:uuid:f7c2b92d-2f4a-4490-99c5-c7f1e095f220"
        },
        "date": "2014-07-06T13:01:59-04:00",
        "primarySource": true,
        "resourceType": "Immunization"
      }
    },
    {
      "fullUrl": "urn:uuid:5d490fb8-824c-4628-85a1-3ff14880f0d2",
      "resource": {
        "id": "5d490fb8-824c-4628-85a1-3ff14880f0d2",
        "meta": {
          "profile": [
            "http://standardhealthrecord.org/fhir/StructureDefinition/shr-encounter-Encounter"
          ]
        },
        "status": "finished",
        "class": {
          "code": "outpatient"
        },
        "type": [
          {
            "coding": [
              {
                "system": "http://snomed.info/sct",
                "code": "185349003"
              }
            ],
            "text": "Outpatient Encounter"
          }
        ],
        "subject": {
          "reference": "urn:uuid:5b81597d-5c6a-47d5-aef1-450bedcb2fb1"
        },
        "period": {
          "start": "2015-07-27T18:21:02-04:00",
          "end": "2015-07-27T19:21:02-04:00"
        },
        "serviceProvider": {
          "reference": "urn:uuid:f59af82d-aee6-48a8-a838-0622308fbb8f"
        },
        "resourceType": "Encounter"
      }
    },
    {
      "fullUrl": "urn:uuid:424b7ef1-3339-4035-9c78-d242777bad11",
      "resource": {
        "id": "424b7ef1-3339-4035-9c78-d242777bad11",
        "meta": {
          "profile": [
            "http://standardhealthrecord.org/fhir/StructureDefinition/shr-observation-Observation",
            "http://standardhealthrecord.org/fhir/StructureDefinition/shr-vital-VitalSign",
            "http://standardhealthrecord.org/fhir/StructureDefinition/shr-vital-BodyHeight"
          ]
        },
        "status": "final",
        "category": [
          {
            "coding": [
              {
                "system": "http://hl7.org/fhir/observation-category",
                "code": "vital-signs"
              }
            ]
          }
        ],
        "code": {
          "coding": [
            {
              "system": "http://loinc.org",
              "code": "8302-2",
              "display": "Body Height"
            }
          ],
          "text": "Body Height"
        },
        "subject": {
          "reference": "urn:uuid:5b81597d-5c6a-47d5-aef1-450bedcb2fb1"
        },
        "context": {
          "reference": "urn:uuid:5d490fb8-824c-4628-85a1-3ff14880f0d2"
        },
        "effectiveDateTime": "2015-07-27T18:21:02-04:00",
        "issued": "2015-07-27T18:21:02-04:00",
        "valueQuantity": {
          "value": 175.09935943534356,
          "unit": "cm",
          "system": "http://unitsofmeasure.org/",
          "code": "cm"
        },
        "resourceType": "Observation"
      }
    },
    {
      "fullUrl": "urn:uuid:a3330f11-bea7-40e0-8de0-9b9d55d86bdc",
      "resource": {
        "id": "a3330f11-bea7-40e0-8de0-9b9d55d86bdc",
        "meta": {
          "profile": [
            "http://standardhealthrecord.org/fhir/StructureDefinition/shr-observation-Observation",
            "http://standardhealthrecord.org/fhir/StructureDefinition/shr-vital-VitalSign",
            "http://standardhealthrecord.org/fhir/StructureDefinition/shr-vital-BodyWeight"
          ]
        },
        "status": "final",
        "category": [
          {
            "coding": [
              {
                "system": "http://hl7.org/fhir/observation-category",
                "code": "vital-signs"
              }
            ]
          }
        ],
        "code": {
          "coding": [
            {
              "system": "http://loinc.org",
              "code": "29463-7",
              "display": "Body Weight"
            }
          ],
          "text": "Body Weight"
        },
        "subject": {
          "reference": "urn:uuid:5b81597d-5c6a-47d5-aef1-450bedcb2fb1"
        },
        "context": {
          "reference": "urn:uuid:5d490fb8-824c-4628-85a1-3ff14880f0d2"
        },
        "effectiveDateTime": "2015-07-27T18:21:02-04:00",
        "issued": "2015-07-27T18:21:02-04:00",
        "valueQuantity": {
          "value": 63.91697960318444,
          "unit": "kg",
          "system": "http://unitsofmeasure.org/",
          "code": "kg"
        },
        "resourceType": "Observation"
      }
    },
    {
      "fullUrl": "urn:uuid:e064bbcd-eae0-4f39-aa83-4b1bd349e62b",
      "resource": {
        "id": "e064bbcd-eae0-4f39-aa83-4b1bd349e62b",
        "meta": {
          "profile": [
            "http://standardhealthrecord.org/fhir/StructureDefinition/shr-observation-Observation",
            "http://standardhealthrecord.org/fhir/StructureDefinition/shr-vital-VitalSign",
            "http://standardhealthrecord.org/fhir/StructureDefinition/shr-vital-BodyMassIndex"
          ]
        },
        "status": "final",
        "category": [
          {
            "coding": [
              {
                "system": "http://hl7.org/fhir/observation-category",
                "code": "vital-signs"
              }
            ]
          }
        ],
        "code": {
          "coding": [
            {
              "system": "http://loinc.org",
              "code": "39156-5",
              "display": "Body Mass Index"
            }
          ],
          "text": "Body Mass Index"
        },
        "subject": {
          "reference": "urn:uuid:5b81597d-5c6a-47d5-aef1-450bedcb2fb1"
        },
        "context": {
          "reference": "urn:uuid:5d490fb8-824c-4628-85a1-3ff14880f0d2"
        },
        "effectiveDateTime": "2015-07-27T18:21:02-04:00",
        "issued": "2015-07-27T18:21:02-04:00",
        "valueQuantity": {
          "value": 20.847171040727545,
          "unit": "kg/m2",
          "system": "http://unitsofmeasure.org/",
          "code": "kg/m2"
        },
        "resourceType": "Observation"
      }
    },
    {
      "fullUrl": "urn:uuid:2db5054e-7872-462e-85ae-4fbb3866dd77",
      "resource": {
        "id": "2db5054e-7872-462e-85ae-4fbb3866dd77",
        "meta": {
          "profile": [
            "http://standardhealthrecord.org/fhir/StructureDefinition/shr-observation-Observation",
            "http://standardhealthrecord.org/fhir/StructureDefinition/shr-vital-BloodPressure"
          ]
        },
        "status": "final",
        "category": [
          {
            "coding": [
              {
                "system": "http://hl7.org/fhir/observation-category",
                "code": "vital-signs"
              }
            ]
          }
        ],
        "code": {
          "coding": [
            {
              "system": "http://loinc.org",
              "code": "55284-4",
              "display": "Blood Pressure"
            }
          ]
        },
        "subject": {
          "reference": "urn:uuid:5b81597d-5c6a-47d5-aef1-450bedcb2fb1"
        },
        "context": {
          "reference": "urn:uuid:5d490fb8-824c-4628-85a1-3ff14880f0d2"
        },
        "effectiveDateTime": "2015-07-27T18:21:02-04:00",
        "issued": "2015-07-27T18:21:02-04:00",
        "component": [
          {
            "code": {
              "coding": [
                {
                  "system": "http://loinc.org",
                  "code": "8480-6",
                  "display": "Systolic Blood Pressure"
                }
              ],
              "text": "Systolic Blood Pressure"
            },
            "valueQuantity": {
              "value": 121,
              "unit": "mmHg",
              "system": "http://unitsofmeasure.org/",
              "code": "mmHg"
            }
          },
          {
            "code": {
              "coding": [
                {
                  "system": "http://loinc.org",
                  "code": "8462-4",
                  "display": "Diastolic Blood Pressure"
                }
              ],
              "text": "Diastolic Blood Pressure"
            },
            "valueQuantity": {
              "value": 78,
              "unit": "mmHg",
              "system": "http://unitsofmeasure.org/",
              "code": "mmHg"
            }
          }
        ],
        "resourceType": "Observation"
      }
    },
    {
      "resource": {
        "meta": {
          "profile": [
            "http://standardhealthrecord.org/fhir/StructureDefinition/shr-immunization-Immunization"
          ]
        },
        "status": "completed",
        "notGiven": false,
        "vaccineCode": {
          "coding": [
            {
              "system": "http://hl7.org/fhir/sid/cvx",
              "code": "140",
              "display": "Influenza, seasonal, injectable, preservative free"
            }
          ],
          "text": "Influenza, seasonal, injectable, preservative free"
        },
        "patient": {
          "reference": "urn:uuid:5b81597d-5c6a-47d5-aef1-450bedcb2fb1"
        },
        "encounter": {
          "reference": "urn:uuid:5d490fb8-824c-4628-85a1-3ff14880f0d2"
        },
        "date": "2015-07-27T18:21:02-04:00",
        "primarySource": true,
        "resourceType": "Immunization"
      }
    }
  ],
  "resourceType": "Bundle"
}